odoo/addons/product_multi_category/README.rst
odoo/addons/product_multi_category/__init__.py
odoo/addons/product_multi_category/__manifest__.py
odoo/addons/product_multi_category/i18n/ca.po
odoo/addons/product_multi_category/i18n/de.po
odoo/addons/product_multi_category/i18n/es.po
odoo/addons/product_multi_category/i18n/fr.po
odoo/addons/product_multi_category/i18n/fr_BE.po
odoo/addons/product_multi_category/i18n/hr.po
odoo/addons/product_multi_category/i18n/nl_NL.po
odoo/addons/product_multi_category/i18n/product_m2mcategories.pot
odoo/addons/product_multi_category/i18n/sv.po
odoo/addons/product_multi_category/i18n/tr.po
odoo/addons/product_multi_category/models/__init__.py
odoo/addons/product_multi_category/models/product.py
odoo/addons/product_multi_category/static/description/icon.png
odoo/addons/product_multi_category/views/product_view.xml
odoo11_addon_product_multi_category-11.0.1.0.0.dist-info/DESCRIPTION.rst
odoo11_addon_product_multi_category-11.0.1.0.0.dist-info/METADATA
odoo11_addon_product_multi_category-11.0.1.0.0.dist-info/RECORD
odoo11_addon_product_multi_category-11.0.1.0.0.dist-info/WHEEL
odoo11_addon_product_multi_category-11.0.1.0.0.dist-info/metadata.json
odoo11_addon_product_multi_category-11.0.1.0.0.dist-info/top_level.txt
